<?xml version="1.0" ?>

<knowledge_base
	xmlns="http://protege.stanford.edu/xml"
	xmlns:xsi="http://www.w3.org/2001/XMLSchema-instance"
	xsi:schemaLocation="http://protege.stanford.edu/xml http://protege.stanford.edu/xml/schema/protege.xsd">

	<class>
		<name>:THING</name>
		<type>:STANDARD-CLASS</type>
		<own_slot_value>
			<slot_reference>:ROLE</slot_reference>
			<value value_type="string">Abstract</value>
		</own_slot_value>
	</class>

	<class>
		<name>:SYSTEM-CLASS</name>
		<type>:STANDARD-CLASS</type>
		<own_slot_value>
			<slot_reference>:ROLE</slot_reference>
			<value value_type="string">Abstract</value>
		</own_slot_value>
		<superclass>:THING</superclass>
	</class>

	<class>
		<name>:STANDARD-CLASS</name>
		<type>:STANDARD-CLASS</type>
		<own_slot_value>
			<slot_reference>:ROLE</slot_reference>
			<value value_type="string">Concrete</value>
		</own_slot_value>
		<superclass>:CLASS</superclass>
		<template_slot>:ROLE</template_slot>
		<template_slot>:DOCUMENTATION</template_slot>
		<template_slot>:SLOT-CONSTRAINTS</template_slot>
	</class>

	<class>
		<name>:STANDARD-SLOT</name>
		<type>:STANDARD-CLASS</type>
		<own_slot_value>
			<slot_reference>:ROLE</slot_reference>
			<value value_type="string">Concrete</value>
		</own_slot_value>
		<superclass>:SLOT</superclass>
		<template_slot>:DOCUMENTATION</template_slot>
		<template_slot>:SLOT-CONSTRAINTS</template_slot>
		<template_slot>:SLOT-MAXIMUM-CARDINALITY</template_slot>
		<template_slot>:SLOT-MINIMUM-CARDINALITY</template_slot>
		<template_slot>:SLOT-NUMERIC-MAXIMUM</template_slot>
		<template_slot>:SLOT-NUMERIC-MINIMUM</template_slot>
		<template_slot>:SLOT-INVERSE</template_slot>
		<template_slot>:SLOT-DEFAULTS</template_slot>
		<template_slot>:SLOT-VALUES</template_slot>
		<template_slot>:ASSOCIATED-FACET</template_slot>
		<template_slot>:DIRECT-SUBSLOTS</template_slot>
		<template_slot>:DIRECT-SUPERSLOTS</template_slot>
	</class>

	<class>
		<name>Plato</name>
		<type>:STANDARD-CLASS</type>
		<own_slot_value>
			<slot_reference>:ROLE</slot_reference>
			<value value_type="string">Concrete</value>
		</own_slot_value>
		<superclass>:THING</superclass>
		<template_slot>nombre</template_slot>
		<template_slot>lugarOrigen</template_slot>
		<template_slot>complejidad</template_slot>
		<template_slot>precio</template_slot>
		<template_slot>es_frio</template_slot>
		<template_slot>tamano</template_slot>
		<template_slot>es_moderno</template_slot>
		<template_slot>disponibilidad</template_slot>
	</class>

	<class>
		<name>Segundo</name>
		<type>:STANDARD-CLASS</type>
		<own_slot_value>
			<slot_reference>:ROLE</slot_reference>
			<value value_type="string">Concrete</value>
		</own_slot_value>
		<superclass>Plato</superclass>
	</class>

	<class>
		<name>Primero</name>
		<type>:STANDARD-CLASS</type>
		<own_slot_value>
			<slot_reference>:ROLE</slot_reference>
			<value value_type="string">Concrete</value>
		</own_slot_value>
		<superclass>Plato</superclass>
	</class>

	<class>
		<name>Hibrido</name>
		<type>:STANDARD-CLASS</type>
		<own_slot_value>
			<slot_reference>:ROLE</slot_reference>
			<value value_type="string">Concrete</value>
		</own_slot_value>
		<superclass>Plato</superclass>
	</class>

	<class>
		<name>Postre</name>
		<type>:STANDARD-CLASS</type>
		<own_slot_value>
			<slot_reference>:ROLE</slot_reference>
			<value value_type="string">Concrete</value>
		</own_slot_value>
		<superclass>Plato</superclass>
	</class>

	<class>
		<name>Menu</name>
		<type>:STANDARD-CLASS</type>
		<own_slot_value>
			<slot_reference>:ROLE</slot_reference>
			<value value_type="string">Concrete</value>
		</own_slot_value>
		<superclass>:THING</superclass>
	</class>

	<class>
		<name>Ingrediente</name>
		<type>:STANDARD-CLASS</type>
		<own_slot_value>
			<slot_reference>:ROLE</slot_reference>
			<value value_type="string">Concrete</value>
		</own_slot_value>
		<superclass>:THING</superclass>
		<template_slot>nombre</template_slot>
		<template_slot>contiene_gluten</template_slot>
		<template_slot>contiene_carne</template_slot>
		<template_slot>contiene_lactosa</template_slot>
		<template_slot>contiene_azucar</template_slot>
	</class>

	<class>
		<name>Bebida</name>
		<type>:STANDARD-CLASS</type>
		<own_slot_value>
			<slot_reference>:ROLE</slot_reference>
			<value value_type="string">Concrete</value>
		</own_slot_value>
		<superclass>:THING</superclass>
		<template_slot>nombre</template_slot>
		<template_slot>precio</template_slot>
		<template_slot>contiene_alcohol</template_slot>
		<template_slot>contiene_azucar</template_slot>
		<template_slot>contiene_lactosa</template_slot>
	</class>

	<slot>
		<name>complejidad</name>
		<type>:STANDARD-SLOT</type>
		<own_slot_value>
			<slot_reference>:DOCUMENTATION</slot_reference>
			<value value_type="string">Entero del [1..5], donde 1 es la m&#237;nima complejidad y 5 la m&#225;xima.</value>
		</own_slot_value>
		<own_slot_value>
			<slot_reference>:SLOT-MAXIMUM-CARDINALITY</slot_reference>
			<value value_type="integer">1</value>
		</own_slot_value>
		<own_slot_value>
			<slot_reference>:SLOT-NUMERIC-MAXIMUM</slot_reference>
			<value value_type="float">5.0</value>
		</own_slot_value>
		<own_slot_value>
			<slot_reference>:SLOT-NUMERIC-MINIMUM</slot_reference>
			<value value_type="float">1.0</value>
		</own_slot_value>
		<own_slot_value>
			<slot_reference>:SLOT-VALUE-TYPE</slot_reference>
			<value value_type="string">Integer</value>
		</own_slot_value>
	</slot>

	<slot>
		<name>contiene_alcohol</name>
		<type>:STANDARD-SLOT</type>
		<own_slot_value>
			<slot_reference>:SLOT-MAXIMUM-CARDINALITY</slot_reference>
			<value value_type="integer">1</value>
		</own_slot_value>
		<own_slot_value>
			<slot_reference>:SLOT-MINIMUM-CARDINALITY</slot_reference>
			<value value_type="integer">1</value>
		</own_slot_value>
		<own_slot_value>
			<slot_reference>:SLOT-VALUE-TYPE</slot_reference>
			<value value_type="string">Boolean</value>
		</own_slot_value>
	</slot>

	<slot>
		<name>contiene_azucar</name>
		<type>:STANDARD-SLOT</type>
		<own_slot_value>
			<slot_reference>:SLOT-MAXIMUM-CARDINALITY</slot_reference>
			<value value_type="integer">1</value>
		</own_slot_value>
		<own_slot_value>
			<slot_reference>:SLOT-VALUE-TYPE</slot_reference>
			<value value_type="string">Boolean</value>
		</own_slot_value>
	</slot>

	<slot>
		<name>contiene_carne</name>
		<type>:STANDARD-SLOT</type>
		<own_slot_value>
			<slot_reference>:SLOT-MAXIMUM-CARDINALITY</slot_reference>
			<value value_type="integer">1</value>
		</own_slot_value>
		<own_slot_value>
			<slot_reference>:SLOT-VALUE-TYPE</slot_reference>
			<value value_type="string">Boolean</value>
		</own_slot_value>
	</slot>

	<slot>
		<name>contiene_gluten</name>
		<type>:STANDARD-SLOT</type>
		<own_slot_value>
			<slot_reference>:SLOT-MAXIMUM-CARDINALITY</slot_reference>
			<value value_type="integer">1</value>
		</own_slot_value>
		<own_slot_value>
			<slot_reference>:SLOT-VALUE-TYPE</slot_reference>
			<value value_type="string">Boolean</value>
		</own_slot_value>
	</slot>

	<slot>
		<name>contiene_lactosa</name>
		<type>:STANDARD-SLOT</type>
		<own_slot_value>
			<slot_reference>:SLOT-MAXIMUM-CARDINALITY</slot_reference>
			<value value_type="integer">1</value>
		</own_slot_value>
		<own_slot_value>
			<slot_reference>:SLOT-VALUE-TYPE</slot_reference>
			<value value_type="string">Boolean</value>
		</own_slot_value>
	</slot>

	<slot>
		<name>disponibilidad</name>
		<type>:STANDARD-SLOT</type>
		<own_slot_value>
			<slot_reference>:DOCUMENTATION</slot_reference>
			<value value_type="string">Valores posibles:
verano
otono
primavera
invierno</value>
		</own_slot_value>
		<own_slot_value>
			<slot_reference>:SLOT-MAXIMUM-CARDINALITY</slot_reference>
			<value value_type="integer">4</value>
		</own_slot_value>
		<own_slot_value>
			<slot_reference>:SLOT-MINIMUM-CARDINALITY</slot_reference>
			<value value_type="integer">1</value>
		</own_slot_value>
		<own_slot_value>
			<slot_reference>:SLOT-VALUE-TYPE</slot_reference>
			<value value_type="string">String</value>
		</own_slot_value>
	</slot>

	<slot>
		<name>es_frio</name>
		<type>:STANDARD-SLOT</type>
		<own_slot_value>
			<slot_reference>:DOCUMENTATION</slot_reference>
			<value value_type="string">if (!es_frio) -&gt; es_caliente</value>
		</own_slot_value>
		<own_slot_value>
			<slot_reference>:SLOT-MAXIMUM-CARDINALITY</slot_reference>
			<value value_type="integer">1</value>
		</own_slot_value>
		<own_slot_value>
			<slot_reference>:SLOT-VALUE-TYPE</slot_reference>
			<value value_type="string">Boolean</value>
		</own_slot_value>
	</slot>

	<slot>
		<name>es_moderno</name>
		<type>:STANDARD-SLOT</type>
		<own_slot_value>
			<slot_reference>:DOCUMENTATION</slot_reference>
			<value value_type="string">if (!es_moderno) -&gt; es_tradicional</value>
		</own_slot_value>
		<own_slot_value>
			<slot_reference>:SLOT-MAXIMUM-CARDINALITY</slot_reference>
			<value value_type="integer">1</value>
		</own_slot_value>
		<own_slot_value>
			<slot_reference>:SLOT-VALUE-TYPE</slot_reference>
			<value value_type="string">Boolean</value>
		</own_slot_value>
	</slot>

	<slot>
		<name>IngredientesPrincipales</name>
		<type>:STANDARD-SLOT</type>
		<own_slot_value>
			<slot_reference>:SLOT-MAXIMUM-CARDINALITY</slot_reference>
			<value value_type="integer">5</value>
		</own_slot_value>
		<own_slot_value>
			<slot_reference>:SLOT-MINIMUM-CARDINALITY</slot_reference>
			<value value_type="integer">1</value>
		</own_slot_value>
		<own_slot_value>
			<slot_reference>:SLOT-VALUE-TYPE</slot_reference>
			<value value_type="string">Class</value>
		</own_slot_value>
	</slot>

	<slot>
		<name>ingredientesPrincipales</name>
		<type>:STANDARD-SLOT</type>
		<own_slot_value>
			<slot_reference>:SLOT-MAXIMUM-CARDINALITY</slot_reference>
			<value value_type="integer">5</value>
		</own_slot_value>
		<own_slot_value>
			<slot_reference>:SLOT-MINIMUM-CARDINALITY</slot_reference>
			<value value_type="integer">1</value>
		</own_slot_value>
		<own_slot_value>
			<slot_reference>:SLOT-VALUE-TYPE</slot_reference>
			<value value_type="string">String</value>
		</own_slot_value>
	</slot>

	<slot>
		<name>lugarOrigen</name>
		<type>:STANDARD-SLOT</type>
		<own_slot_value>
			<slot_reference>:SLOT-MAXIMUM-CARDINALITY</slot_reference>
			<value value_type="integer">1</value>
		</own_slot_value>
		<own_slot_value>
			<slot_reference>:SLOT-VALUE-TYPE</slot_reference>
			<value value_type="string">String</value>
		</own_slot_value>
	</slot>

	<slot>
		<name>nombre</name>
		<type>:STANDARD-SLOT</type>
		<own_slot_value>
			<slot_reference>:SLOT-MAXIMUM-CARDINALITY</slot_reference>
			<value value_type="integer">1</value>
		</own_slot_value>
		<own_slot_value>
			<slot_reference>:SLOT-VALUE-TYPE</slot_reference>
			<value value_type="string">String</value>
		</own_slot_value>
	</slot>

	<slot>
		<name>precio</name>
		<type>:STANDARD-SLOT</type>
		<own_slot_value>
			<slot_reference>:SLOT-MAXIMUM-CARDINALITY</slot_reference>
			<value value_type="integer">1</value>
		</own_slot_value>
		<own_slot_value>
			<slot_reference>:SLOT-VALUE-TYPE</slot_reference>
			<value value_type="string">Float</value>
		</own_slot_value>
	</slot>

	<slot>
		<name>tamano</name>
		<type>:STANDARD-SLOT</type>
		<own_slot_value>
			<slot_reference>:DOCUMENTATION</slot_reference>
			<value value_type="string">Entero entre [1..5] donde 1 es la raci&#243;n m&#225;s peque&#241;a y 5 la m&#225;s grande.</value>
		</own_slot_value>
		<own_slot_value>
			<slot_reference>:SLOT-MAXIMUM-CARDINALITY</slot_reference>
			<value value_type="integer">1</value>
		</own_slot_value>
		<own_slot_value>
			<slot_reference>:SLOT-NUMERIC-MAXIMUM</slot_reference>
			<value value_type="float">5.0</value>
		</own_slot_value>
		<own_slot_value>
			<slot_reference>:SLOT-NUMERIC-MINIMUM</slot_reference>
			<value value_type="float">1.0</value>
		</own_slot_value>
		<own_slot_value>
			<slot_reference>:SLOT-VALUE-TYPE</slot_reference>
			<value value_type="string">Integer</value>
		</own_slot_value>
	</slot>
</knowledge_base>
